[{"unMeta":{}},[{"t":"Para","c":[{"t":"Str","c":"Consultas"},{"t":"Space","c":[]},{"t":"Str","c":"MongoDB"}]},{"t":"Para","c":[{"t":"Str","c":"1."}]},{"t":"Para","c":[{"t":"Str","c":"db.restaurants.find()"}]},{"t":"Para","c":[{"t":"Str","c":"2."}]},{"t":"Para","c":[{"t":"Str","c":"db.restaurants.find({},{restaurant_id:1,"},{"t":"Space","c":[]},{"t":"Str","c":"name:"},{"t":"Space","c":[]},{"t":"Str","c":"1,"},{"t":"Space","c":[]},{"t":"Str","c":"borough:"},{"t":"Space","c":[]},{"t":"Str","c":"1,"},{"t":"Space","c":[]},{"t":"Str","c":"cuisine:1})"}]},{"t":"Para","c":[{"t":"Str","c":"3."}]},{"t":"Para","c":[{"t":"Str","c":"db.restaurants.find({},{restaurant_id:1,"},{"t":"Space","c":[]},{"t":"Str","c":"name:"},{"t":"Space","c":[]},{"t":"Str","c":"1,"},{"t":"Space","c":[]},{"t":"Str","c":"borough:"},{"t":"Space","c":[]},{"t":"Str","c":"1,"},{"t":"Space","c":[]},{"t":"Str","c":"cuisine:1,"},{"t":"Space","c":[]},{"t":"Str","c":"_id:0})"}]},{"t":"Para","c":[{"t":"Str","c":"4."}]},{"t":"Para","c":[{"t":"Str","c":"db.restaurants.find({},{restaurant_id:1,"},{"t":"Space","c":[]},{"t":"Str","c":"name:"},{"t":"Space","c":[]},{"t":"Str","c":"1,"},{"t":"Space","c":[]},{"t":"Str","c":"borough:"},{"t":"Space","c":[]},{"t":"Str","c":"1,"},{"t":"Space","c":[]},{"t":"Str","c":"address:{zipcode:1},"},{"t":"Space","c":[]},{"t":"Str","c":"_id:0})"}]},{"t":"Para","c":[{"t":"Str","c":"5."}]},{"t":"Para","c":[{"t":"Str","c":"db.restaurants.find({“borough”:"},{"t":"Space","c":[]},{"t":"Str","c":"“Bronx”})"}]},{"t":"Para","c":[{"t":"Str","c":"6."}]},{"t":"Para","c":[{"t":"Str","c":"db.restaurants.find({\"borough\":"},{"t":"Space","c":[]},{"t":"Str","c":"\"Bronx\"}).limit(5)"}]},{"t":"Para","c":[{"t":"Str","c":"7."}]},{"t":"Para","c":[{"t":"Str","c":"db.restaurants.find({\"borough\":"},{"t":"Space","c":[]},{"t":"Str","c":"\"Bronx\"}).skip(5).limit(5)"}]},{"t":"Para","c":[{"t":"Str","c":"8."}]},{"t":"Para","c":[{"t":"Str","c":"db.restaurants.find({\"grades.score\":"},{"t":"Space","c":[]},{"t":"Str","c":"{$gt:90}})"}]},{"t":"Para","c":[{"t":"Str","c":"9."}]},{"t":"Para","c":[{"t":"Str","c":"db.restaurants.find({$or:"},{"t":"Space","c":[]},{"t":"Str","c":"[{\"grades.score\":"},{"t":"Space","c":[]},{"t":"Str","c":"{$gt:80}},"},{"t":"Space","c":[]},{"t":"Str","c":"{\"grades.score\":{$lt:"},{"t":"Space","c":[]},{"t":"Str","c":"100}}]})"}]},{"t":"Para","c":[{"t":"Str","c":"10."}]},{"t":"Para","c":[{"t":"Str","c":"db.restaurants.find({"},{"t":"Space","c":[]},{"t":"Str","c":"\"address.coord.0\""},{"t":"Space","c":[]},{"t":"Str","c":":"},{"t":"Space","c":[]},{"t":"Str","c":"{"},{"t":"Space","c":[]},{"t":"Str","c":"$lt"},{"t":"Space","c":[]},{"t":"Str","c":":"},{"t":"Space","c":[]},{"t":"Str","c":"-95.754168"},{"t":"Space","c":[]},{"t":"Str","c":"}})"}]},{"t":"Para","c":[{"t":"Str","c":"11."}]},{"t":"Para","c":[{"t":"Str","c":"db.restaurants.find({"},{"t":"Space","c":[]},{"t":"Str","c":"cuisine:"},{"t":"Space","c":[]},{"t":"Str","c":"{$ne:"},{"t":"Space","c":[]},{"t":"Str","c":"\"American"},{"t":"Space","c":[]},{"t":"Str","c":"\"},"},{"t":"Space","c":[]},{"t":"Str","c":"\"grades.score\":"},{"t":"Space","c":[]},{"t":"Str","c":"{$gt:"},{"t":"Space","c":[]},{"t":"Str","c":"70},"},{"t":"Space","c":[]},{"t":"Str","c":"\"address.coord.0\":"},{"t":"Space","c":[]},{"t":"Str","c":"{$lt:"},{"t":"Space","c":[]},{"t":"Str","c":"-65.754168}"},{"t":"Space","c":[]},{"t":"Str","c":"})"}]},{"t":"Para","c":[{"t":"Str","c":"12."}]},{"t":"Para","c":[{"t":"Str","c":"db.restaurants.find({"},{"t":"Space","c":[]},{"t":"Str","c":"$and"},{"t":"Space","c":[]},{"t":"Str","c":":"},{"t":"Space","c":[]},{"t":"Str","c":"["},{"t":"Space","c":[]},{"t":"Str","c":"{"},{"t":"Space","c":[]},{"t":"Str","c":"cuisine"},{"t":"Space","c":[]},{"t":"Str","c":":"},{"t":"Space","c":[]},{"t":"Str","c":"{"},{"t":"Space","c":[]},{"t":"Str","c":"$ne"},{"t":"Space","c":[]},{"t":"Str","c":":"},{"t":"Space","c":[]},{"t":"Str","c":"\"American"},{"t":"Space","c":[]},{"t":"Str","c":"\""},{"t":"Space","c":[]},{"t":"Str","c":"}},"},{"t":"Space","c":[]},{"t":"Str","c":"{"},{"t":"Space","c":[]},{"t":"Str","c":"\"grades.score\""},{"t":"Space","c":[]},{"t":"Str","c":":"},{"t":"Space","c":[]},{"t":"Str","c":"{"},{"t":"Space","c":[]},{"t":"Str","c":"$gt:"},{"t":"Space","c":[]},{"t":"Str","c":"70"},{"t":"Space","c":[]},{"t":"Str","c":"}},"},{"t":"Space","c":[]},{"t":"Str","c":"{"},{"t":"Space","c":[]},{"t":"Str","c":"\"address.coord\""},{"t":"Space","c":[]},{"t":"Str","c":":"},{"t":"Space","c":[]},{"t":"Str","c":"{"},{"t":"Space","c":[]},{"t":"Str","c":"$lt:"},{"t":"Space","c":[]},{"t":"Str","c":"-65.754168}"},{"t":"Space","c":[]},{"t":"Str","c":"}]})"}]},{"t":"Para","c":[{"t":"Str","c":"13."}]},{"t":"Para","c":[{"t":"Str","c":"db.restaurants.find({"},{"t":"Space","c":[]},{"t":"Str","c":"cuisine"},{"t":"Space","c":[]},{"t":"Str","c":":"},{"t":"Space","c":[]},{"t":"Str","c":"{$ne:"},{"t":"Space","c":[]},{"t":"Str","c":"\"American"},{"t":"Space","c":[]},{"t":"Str","c":"\"},"},{"t":"Space","c":[]},{"t":"Str","c":"\"grades.grade\""},{"t":"Space","c":[]},{"t":"Str","c":":"},{"t":"Space","c":[]},{"t":"Str","c":"\"A\","},{"t":"Space","c":[]},{"t":"Str","c":"\"borough\""},{"t":"Space","c":[]},{"t":"Str","c":":"},{"t":"Space","c":[]},{"t":"Str","c":"{$ne"},{"t":"Space","c":[]},{"t":"Str","c":":"},{"t":"Space","c":[]},{"t":"Str","c":"\"Brooklyn\"}"},{"t":"Space","c":[]},{"t":"Str","c":"}).sort({cuisine:"},{"t":"Space","c":[]},{"t":"Str","c":"-1})"}]},{"t":"Para","c":[{"t":"Str","c":"14."}]},{"t":"Para","c":[{"t":"Str","c":"db.restaurants.find("},{"t":"Space","c":[]},{"t":"Str","c":"{"},{"t":"Space","c":[]},{"t":"Str","c":"name:"},{"t":"Space","c":[]},{"t":"Str","c":"{$regex:"},{"t":"Space","c":[]},{"t":"Str","c":"\"^Wil\"}},"},{"t":"Space","c":[]},{"t":"Str","c":"{"},{"t":"Space","c":[]},{"t":"Str","c":"restaurant_id:1,"},{"t":"Space","c":[]},{"t":"Str","c":"name:1,"},{"t":"Space","c":[]},{"t":"Str","c":"borough:1,"},{"t":"Space","c":[]},{"t":"Str","c":"cuisine:"},{"t":"Space","c":[]},{"t":"Str","c":"1,"},{"t":"Space","c":[]},{"t":"Str","c":"_id:0"},{"t":"Space","c":[]},{"t":"Str","c":"})"}]},{"t":"Para","c":[{"t":"Str","c":"15."}]},{"t":"Para","c":[{"t":"Str","c":"db.restaurants.find({"},{"t":"Space","c":[]},{"t":"Str","c":"name:"},{"t":"Space","c":[]},{"t":"Str","c":"{$regex:"},{"t":"Space","c":[]},{"t":"Str","c":"\"ces$\"}},"},{"t":"Space","c":[]},{"t":"Str","c":"{"},{"t":"Space","c":[]},{"t":"Str","c":"restaurant_id:1,"},{"t":"Space","c":[]},{"t":"Str","c":"name:1,"},{"t":"Space","c":[]},{"t":"Str","c":"borough:1,"},{"t":"Space","c":[]},{"t":"Str","c":"cuisine:"},{"t":"Space","c":[]},{"t":"Str","c":"1,"},{"t":"Space","c":[]},{"t":"Str","c":"_id:0"},{"t":"Space","c":[]},{"t":"Str","c":"}"},{"t":"Space","c":[]},{"t":"Str","c":")"}]},{"t":"Para","c":[{"t":"Str","c":"16."}]},{"t":"Para","c":[{"t":"Str","c":"db.restaurants.find("},{"t":"Space","c":[]},{"t":"Str","c":"{"},{"t":"Space","c":[]},{"t":"Str","c":"name"},{"t":"Space","c":[]},{"t":"Str","c":":"},{"t":"Space","c":[]},{"t":"Str","c":"{$regex:"},{"t":"Space","c":[]},{"t":"Str","c":"\"Reg\"}},"},{"t":"Space","c":[]},{"t":"Str","c":"{"},{"t":"Space","c":[]},{"t":"Str","c":"restaurant_id:1,"},{"t":"Space","c":[]},{"t":"Str","c":"name:1,"},{"t":"Space","c":[]},{"t":"Str","c":"borough:1,"},{"t":"Space","c":[]},{"t":"Str","c":"cuisine:"},{"t":"Space","c":[]},{"t":"Str","c":"1,"},{"t":"Space","c":[]},{"t":"Str","c":"_id:0"},{"t":"Space","c":[]},{"t":"Str","c":"}"},{"t":"Space","c":[]},{"t":"Str","c":")"}]},{"t":"Para","c":[{"t":"Str","c":"17."}]},{"t":"Para","c":[{"t":"Str","c":"db.restaurants.find("},{"t":"Space","c":[]},{"t":"Str","c":"{borough:"},{"t":"Space","c":[]},{"t":"Str","c":"{"},{"t":"Space","c":[]},{"t":"Str","c":"$eq:"},{"t":"Space","c":[]},{"t":"Str","c":"\"Bronx\""},{"t":"Space","c":[]},{"t":"Str","c":"},"},{"t":"Space","c":[]},{"t":"Str","c":"cuisine:"},{"t":"Space","c":[]},{"t":"Str","c":"{"},{"t":"Space","c":[]},{"t":"Str","c":"$in:"},{"t":"Space","c":[]},{"t":"Str","c":"[\"American"},{"t":"Space","c":[]},{"t":"Str","c":"\","},{"t":"Space","c":[]},{"t":"Str","c":"\"Chinese\"]}})"}]},{"t":"Para","c":[{"t":"Str","c":"18."}]},{"t":"Para","c":[{"t":"Str","c":"db.restaurants.find({"},{"t":"Space","c":[]},{"t":"Str","c":"$or:"},{"t":"Space","c":[]},{"t":"Str","c":"[{borough:\"Staten"},{"t":"Space","c":[]},{"t":"Str","c":"Island\"},{borough:\"Queens\"},{borough:\"Bronx\"},"},{"t":"Space","c":[]},{"t":"Str","c":"{borough:\"Brooklyn\"}]},{_id:0,"},{"t":"Space","c":[]},{"t":"Str","c":"restaurant_id:1,name:1,borough:1,cuisine:1})"}]},{"t":"Para","c":[{"t":"Str","c":"19."}]},{"t":"Para","c":[{"t":"Str","c":"db.restaurants.find({"},{"t":"Space","c":[]},{"t":"Str","c":"$nor:"},{"t":"Space","c":[]},{"t":"Str","c":"[{borough:\"Staten"},{"t":"Space","c":[]},{"t":"Str","c":"Island\"},{borough:\"Queens\"},{borough:\"Bronx\"},"},{"t":"Space","c":[]},{"t":"Str","c":"{borough:\"Brooklyn\"}]},{_id:0,"},{"t":"Space","c":[]},{"t":"Str","c":"restaurant_id:1,name:1,borough:1,cuisine:1})"}]},{"t":"Para","c":[{"t":"Str","c":"20."}]},{"t":"Para","c":[{"t":"Str","c":"db.restaurants.find({"},{"t":"Space","c":[]},{"t":"Str","c":"\"grades.score\":"},{"t":"Space","c":[]},{"t":"Str","c":"{$lte:10}},{_id:0,"},{"t":"Space","c":[]},{"t":"Str","c":"restaurant_id:1,name:1,borough:1,cuisine:1})"}]}]]